README.md
setup.py
pycn/__init__.py
pythcn.egg-info/PKG-INFO
pythcn.egg-info/SOURCES.txt
pythcn.egg-info/dependency_links.txt
pythcn.egg-info/top_level.txt