Metadata-Version: 2.1
Name: pythcn
Version: 0.0.6
Summary: Python中文式编程——Pythcn，简称pycn
Home-page: https://github.com/
Author: Jianrui Li
Author-email: lijianrui7560@qq.com
Classifier: Programming Language :: Python :: 3
Classifier: License :: OSI Approved :: MIT License
Classifier: Operating System :: OS Independent
